embo/VERSION
embo/__init__.py
embo/core.py
embo/utils.py
embo/examples/Basic-Example.ipynb
embo/examples/Compare-embo-dit.ipynb
embo/examples/Deterministic-Bottleneck.ipynb
embo/examples/Markov-Chains.ipynb
embo/examples/README.md
embo/examples/style.mplstyle
embo/test/__init__.py
embo/test/test_embo.py
embo-1.1.0.dist-info/LICENSE
embo-1.1.0.dist-info/METADATA
embo-1.1.0.dist-info/WHEEL
embo-1.1.0.dist-info/top_level.txt
embo-1.1.0.dist-info/RECORD
