Metadata-Version: 2.1
Name: embo
Version: 1.1.0
Summary: Empirical Information Bottleneck
Home-page: https://gitlab.com/epiasini/embo
Author: Eugenio Piasini
Author-email: epiasini@sas.upenn.edu
License: GPLv3+
Platform: UNKNOWN
Classifier: Development Status :: 4 - Beta
Classifier: Intended Audience :: Science/Research
Classifier: Topic :: Scientific/Engineering :: Information Analysis
Classifier: License :: OSI Approved :: GNU General Public License v3 or later (GPLv3+)
Classifier: Programming Language :: Python :: 3
Classifier: Operating System :: OS Independent
Classifier: Environment :: Console
Requires-Python: >=3
Requires-Dist: numpy (>=1.7)
Requires-Dist: scipy
